praline/config/__init__.py
praline/config/_base.py
praline/config/env.py
praline/config/helpers.py
praline/config/logging.py
praline/config/model.py
praline_config-0.1.3.dist-info/licenses/LICENSE
praline_config-0.1.3.dist-info/METADATA
praline_config-0.1.3.dist-info/PKG-INFO.sync-conflict-20241020-130919-UN3KI43
praline_config-0.1.3.dist-info/WHEEL
praline_config-0.1.3.dist-info/top_level.txt
praline_config-0.1.3.dist-info/RECORD
