Metadata-Version: 2.4
Name: praline-config
Version: 0.1.3
Summary: Easy app configuration.
Author-email: Matthew Galbraith <cuelindar.github@applogins.net>
Project-URL: Homepage, https://github.com/hackmonkey/praline-config
Project-URL: Issues, https://github.com/hackmonkey/praline-config/issues
Classifier: Programming Language :: Python :: 3
Classifier: License :: OSI Approved :: MIT License
Classifier: Operating System :: OS Independent
Classifier: Development Status :: 3 - Alpha
Classifier: Intended Audience :: Developers
Classifier: Topic :: Software Development :: Libraries
Classifier: Topic :: Software Development :: Libraries :: Python Modules
Requires-Python: >=3.11
License-File: LICENSE
Requires-Dist: python-configuration
Requires-Dist: python-dotenv
Requires-Dist: PyYAML
Provides-Extra: dev
Requires-Dist: pytest; extra == "dev"
Requires-Dist: ruff; extra == "dev"
Dynamic: license-file
